<annotation>
  <folder>2007</folder>
  <filename>2007_001073.jpg</filename>
  <source>
    <database>Unknown</database>
    <annotation>Unknown</annotation>
    <image>Unknown</image>
  </source>
  <size>
    <width>500</width>
    <height>375</height>
    <depth></depth>
  </size>
  <segmented>0</segmented>
  <object>
    <name>cow</name>
    <occluded>0</occluded>
    <bndbox>
      <xmin>226.0</xmin>
      <ymin>148.0</ymin>
      <xmax>277.0</xmax>
      <ymax>246.0</ymax>
    </bndbox>
  </object>
  <object>
    <name>cow</name>
    <occluded>0</occluded>
    <bndbox>
      <xmin>130.0</xmin>
      <ymin>175.0</ymin>
      <xmax>171.0</xmax>
      <ymax>238.0</ymax>
    </bndbox>
  </object>
  <object>
    <name>cow</name>
    <occluded>0</occluded>
    <bndbox>
      <xmin>420.0</xmin>
      <ymin>164.0</ymin>
      <xmax>493.0</xmax>
      <ymax>217.0</ymax>
    </bndbox>
  </object>
  <object>
    <name>cow</name>
    <occluded>0</occluded>
    <bndbox>
      <xmin>270.0</xmin>
      <ymin>151.0</ymin>
      <xmax>338.0</xmax>
      <ymax>256.0</ymax>
    </bndbox>
  </object>
  <object>
    <name>cow</name>
    <occluded>0</occluded>
    <bndbox>
      <xmin>53.0</xmin>
      <ymin>176.0</ymin>
      <xmax>147.0</xmax>
      <ymax>246.0</ymax>
    </bndbox>
  </object>
  <object>
    <name>cow</name>
    <occluded>0</occluded>
    <bndbox>
      <xmin>444.0</xmin>
      <ymin>147.0</ymin>
      <xmax>490.0</xmax>
      <ymax>165.0</ymax>
    </bndbox>
  </object>
  <object>
    <name>person</name>
    <occluded>0</occluded>
    <bndbox>
      <xmin>174.0</xmin>
      <ymin>147.0</ymin>
      <xmax>194.0</xmax>
      <ymax>195.0</ymax>
    </bndbox>
  </object>
  <object>
    <name>cow</name>
    <occluded>0</occluded>
    <bndbox>
      <xmin>326.0</xmin>
      <ymin>144.0</ymin>
      <xmax>424.0</xmax>
      <ymax>242.0</ymax>
    </bndbox>
  </object>
  <object>
    <name>cow</name>
    <occluded>0</occluded>
    <bndbox>
      <xmin>463.0</xmin>
      <ymin>149.0</ymin>
      <xmax>486.0</xmax>
      <ymax>162.0</ymax>
    </bndbox>
  </object>
</annotation>
