<annotation>
  <folder>2007</folder>
  <filename>2007_000636.jpg</filename>
  <source>
    <database>Unknown</database>
    <annotation>Unknown</annotation>
    <image>Unknown</image>
  </source>
  <size>
    <width>500</width>
    <height>335</height>
    <depth></depth>
  </size>
  <segmented>0</segmented>
  <object>
    <name>train</name>
    <occluded>0</occluded>
    <bndbox>
      <xmin>40.0</xmin>
      <ymin>86.0</ymin>
      <xmax>444.0</xmax>
      <ymax>292.0</ymax>
    </bndbox>
  </object>
  <object>
    <name>person</name>
    <occluded>0</occluded>
    <bndbox>
      <xmin>47.0</xmin>
      <ymin>147.0</ymin>
      <xmax>61.0</xmax>
      <ymax>194.0</ymax>
    </bndbox>
  </object>
  <object>
    <name>person</name>
    <occluded>0</occluded>
    <bndbox>
      <xmin>443.0</xmin>
      <ymin>156.0</ymin>
      <xmax>450.0</xmax>
      <ymax>171.0</ymax>
    </bndbox>
  </object>
  <object>
    <name>person</name>
    <occluded>0</occluded>
    <bndbox>
      <xmin>436.0</xmin>
      <ymin>157.0</ymin>
      <xmax>443.0</xmax>
      <ymax>171.0</ymax>
    </bndbox>
  </object>
  <object>
    <name>person</name>
    <occluded>0</occluded>
    <bndbox>
      <xmin>468.0</xmin>
      <ymin>160.0</ymin>
      <xmax>483.0</xmax>
      <ymax>195.0</ymax>
    </bndbox>
  </object>
  <object>
    <name>person</name>
    <occluded>0</occluded>
    <bndbox>
      <xmin>449.0</xmin>
      <ymin>156.0</ymin>
      <xmax>456.0</xmax>
      <ymax>172.0</ymax>
    </bndbox>
  </object>
  <object>
    <name>person</name>
    <occluded>0</occluded>
    <bndbox>
      <xmin>458.0</xmin>
      <ymin>160.0</ymin>
      <xmax>478.0</xmax>
      <ymax>194.0</ymax>
    </bndbox>
  </object>
  <object>
    <name>person</name>
    <occluded>0</occluded>
    <bndbox>
      <xmin>444.0</xmin>
      <ymin>156.0</ymin>
      <xmax>448.0</xmax>
      <ymax>162.0</ymax>
    </bndbox>
  </object>
  <object>
    <name>person</name>
    <occluded>0</occluded>
    <bndbox>
      <xmin>439.0</xmin>
      <ymin>152.0</ymin>
      <xmax>454.0</xmax>
      <ymax>176.0</ymax>
    </bndbox>
  </object>
</annotation>
